travis_solo.py
travis_solo-0.0.9.data/scripts/travis-solo
travis_solo-0.0.9.dist-info/DESCRIPTION.rst
travis_solo-0.0.9.dist-info/entry_points.txt
travis_solo-0.0.9.dist-info/METADATA
travis_solo-0.0.9.dist-info/pydist.json
travis_solo-0.0.9.dist-info/RECORD
travis_solo-0.0.9.dist-info/top_level.txt
travis_solo-0.0.9.dist-info/WHEEL
